<?xml version="1.0" encoding="UTF-8"?>
<!DOCTYPE hibernate-mapping PUBLIC "-//Hibernate/Hibernate Mapping DTD 3.0//EN"
"http://hibernate.sourceforge.net/hibernate-mapping-3.0.dtd">

<hibernate-mapping>
	<class name="lyh.po.school.School" table="school">
		<id name="scid" type="java.lang.Integer">
			<column name="SCID" precision="11" scale="0" />
			<generator class="native" />
		</id>
		
		<property name="name" type="java.lang.String">
			<column name="NAME" length="50" not-null="true" />
		</property>
		<property name="scode" type="java.lang.String">
			<column name="SCODE" length="50" not-null="true" />
		</property>
		<property name="email" type="java.lang.String">
			<column name="EMAIL" length="50" not-null="true" />
		</property>
		<property name="address" type="java.lang.String">
			<column name="ADDRESS" length="255" not-null="true" />
		</property>
		<property name="officetel" type="java.lang.String">
			<column name="OFFICETEL" length="50" not-null="true" />
		</property>
		<property name="fax" type="java.lang.String">
			<column name="FAX" length="50" not-null="true" />
		</property>
		<many-to-one name="member" class="lyh.po.user.Member" fetch="select">
			<column name="UID" precision="11"  scale="0" not-null="true" />
		</many-to-one>
	</class>
</hibernate-mapping>
